.gcloudignore
.gitignore
.project
.pydevproject
MANIFEST.in
README.md
app-flex-production.yaml
app-flex-staging.yaml
app.yaml
env_variables.yaml
gae-service-account-key.json
main.py
requirements.txt
setup.cfg
setup.py
start_local.sh
uninstall.txt
tests/__init__.py
tests/test_payment_util.py
trex_payment.egg-info/PKG-INFO
trex_payment.egg-info/SOURCES.txt
trex_payment.egg-info/dependency_links.txt
trex_payment.egg-info/requires.txt
trex_payment.egg-info/top_level.txt
trexpayment/__init__.py
trexpayment/conf.py
trexpayment/product_conf.py
trexpayment/controllers/__init__.py
trexpayment/controllers/main_routes.py
trexpayment/controllers/event/__init__.py
trexpayment/controllers/event/event_routes.py
trexpayment/controllers/integration/__init__.py
trexpayment/controllers/integration/checkout_routes.py
trexpayment/controllers/integration/integrate_routes.py
trexpayment/controllers/payment/__init__.py
trexpayment/controllers/payment/payment_routes.py
trexpayment/controllers/system/__init__.py
trexpayment/controllers/system/custom_routes.py
trexpayment/controllers/system/system_routes.py
trexpayment/decorators/__init__.py
trexpayment/decorators/stripe_webhook_decorators.py
trexpayment/models/__init__.py
trexpayment/models/datastore/__init__.py
trexpayment/models/datastore/payment_models.py
trexpayment/static/__init__.py
trexpayment/static/app/__init__.py
trexpayment/static/app/assets/__init__.py
trexpayment/static/app/assets/css/__init__.py
trexpayment/static/app/assets/css/main.css
trexpayment/static/app/assets/css/shared/__init__.py
trexpayment/static/app/assets/css/shared/bootstrap-datetimepicker-standalone.css
trexpayment/static/app/assets/css/shared/bootstrap-datetimepicker.css
trexpayment/static/app/assets/css/shared/bootstrap-datetimepicker.min.css
trexpayment/static/app/assets/css/shared/notify.css
trexpayment/static/app/assets/css/shared/notify.min.css
trexpayment/static/app/assets/image/__init__.py
trexpayment/static/app/assets/image/icon/__init__.py
trexpayment/static/app/assets/image/icon/icon-email-white.png
trexpayment/static/app/assets/image/icon/icon-nav-notify.png
trexpayment/static/app/assets/image/icon/icon-nav-search.png
