Metadata-Version: 2.1
Name: trex-payment
Version: 0.0.5
Summary: TRex Payment library package
Home-page: https://bitbucket.org/lokjac/trex-payment
Author: Jack Lok
Author-email: sglok77@gmail.com
License: UNKNOWN
Platform: UNKNOWN
Classifier: Programming Language :: Python :: 3
Classifier: License :: OSI Approved :: MIT License
Classifier: Operating System :: OS Independent
